modpack_ch_installer/__init__.py
modpack_ch_installer/__main__.py
modpack_ch_installer/main.py
modpack_ch_installer-1.1.2.dist-info/entry_points.txt
modpack_ch_installer-1.1.2.dist-info/WHEEL
modpack_ch_installer-1.1.2.dist-info/METADATA
modpack_ch_installer-1.1.2.dist-info/RECORD
